niekas/__init__.py
niekas/nested_list.py
tests/__init__.py
tests/test_nested_list.py
pylibre-0.0.2.dist-info/METADATA
pylibre-0.0.2.dist-info/WHEEL
pylibre-0.0.2.dist-info/top_level.txt
pylibre-0.0.2.dist-info/RECORD
