Metadata-Version: 2.1
Name: pylibre
Version: 0.0.2
Summary: Testing Python package creation
Home-page: https://github.com/pypa/sampleproject
Author: niekas
Author-email: albertasgim@gmail.com
License: UNKNOWN
Platform: UNKNOWN
Classifier: Programming Language :: Python :: 3
Classifier: License :: OSI Approved :: MIT License
Classifier: Operating System :: OS Independent
